psplpy/__init__.py
psplpy/autogui_util.py
psplpy/concurrency_utils.py
psplpy/dynamic_compose.py
psplpy/file_utils.py
psplpy/image_det.py
psplpy/image_utils.py
psplpy/middleware_utils.py
psplpy/mp_http.py
psplpy/network_utils.py
psplpy/ocr_utils.py
psplpy/other_utils.py
psplpy/serialization_utils.py
psplpy/django_utils/__init__.py
psplpy/django_utils/database.py
psplpy/django_utils/django_init.py
psplpy/django_utils/enums.py
psplpy/django_utils/settings.py
psplpy/django_utils/templates.py
psplpy/django_utils/utils.py
psplpy/django_utils/resources/apps/accounts/admin.py
psplpy/django_utils/resources/apps/accounts/forms.py
psplpy/django_utils/resources/apps/accounts/models.py
psplpy/django_utils/resources/apps/accounts/urls.py
psplpy/django_utils/resources/apps/accounts/views.py
psplpy/django_utils/resources/templates/base.html
psplpy/django_utils/resources/templates/registration/logged_out.html
psplpy/django_utils/resources/templates/registration/login.html
psplpy/django_utils/resources/templates/registration/password_change_done.html
psplpy/django_utils/resources/templates/registration/password_change_form.html
psplpy/django_utils/resources/templates/registration/password_reset_complete.html
psplpy/django_utils/resources/templates/registration/password_reset_confirm.html
psplpy/django_utils/resources/templates/registration/password_reset_done.html
psplpy/django_utils/resources/templates/registration/password_reset_form.html
psplpy/django_utils/resources/templates/registration/register.html
psplpy/scripts/block_jetbrains.py
psplpy/scripts/count_code_lines.py
psplpy/scripts/fix_labelImg.py
psplpy/scripts/ip.json
psplpy/scripts/save_hoi4.py
psplpy/scripts/speed_test.py
psplpy/scripts/upload_pypi_project.py
psplpy-1.27.2.dist-info/METADATA
psplpy-1.27.2.dist-info/WHEEL
psplpy-1.27.2.dist-info/top_level.txt
psplpy-1.27.2.dist-info/RECORD
