Metadata-Version: 2.1
Name: psplpy
Version: 1.27.2
Summary: The Personal Study Purposes Library of PYthon.
Classifier: Programming Language :: Python :: 3
Classifier: License :: OSI Approved :: MIT License
Classifier: Operating System :: OS Independent
Requires-Python: >=3.10
Requires-Dist: pika
Requires-Dist: pyyaml
Requires-Dist: pyshark
Requires-Dist: opencv-python
Requires-Dist: opencv-python-headless
Requires-Dist: pillow<=9.5.0
Requires-Dist: django
Requires-Dist: channels
Requires-Dist: channels_redis
Requires-Dist: gunicorn
Requires-Dist: uvicorn
Requires-Dist: daphne
Requires-Dist: phonenumbers
Requires-Dist: django-phonenumber-field
Requires-Dist: requests
Requires-Dist: pyautogui
Requires-Dist: pynput
Requires-Dist: numpy<=1.26.4
Requires-Dist: selenium
Requires-Dist: psycopg2-binary
Requires-Dist: aiohttp
